industryts/__init__.py
industryts/main.py
industryts/generation/__init__.py
industryts/generation/synthetic.py
industryts/models/__init__.py
industryts/models/univariate.py
industryts/processing/__init__.py
industryts/processing/featureengineering.py
industryts/processing/filtering.py
industryts/processing/timestamps.py
industryts-1.0.1.dist-info/LICENSE
industryts-1.0.1.dist-info/METADATA
industryts-1.0.1.dist-info/WHEEL
industryts-1.0.1.dist-info/top_level.txt
industryts-1.0.1.dist-info/RECORD
